{
  "name": "Everest Tokenlist",
  "logoURI": "https://i.imgur.com/Mm0gPhL.png",
  "version": {
    "major": 0,
    "minor": 3,
    "patch": 0
  },
  "keywords": [],
  "timestamp": "2022-05-13T00:00:00+00:00",
  "tokens": [
    {
      "address": "0xd92FB2844E76e455DfD0e20D46BCA2Cc77558B6e",
      "chainId": 552,
      "name": "Wrapped ICY",
      "symbol": "WICY",
      "decimals": 18,
      "logoURI": "https://i.imgur.com/FRUIJUV.png"
    },
    {
      "address": "0xE0A1967379fEB47966F4B315abc8d941C158F165",
      "chainId": 552,
      "name": "Equality",
      "symbol": "EQU",
      "decimals": 18,
      "logoURI": "https://i.imgur.com/hUIAxqW.png"
    },
    {
      "address": "0x1fAA9fD35b140EeDf9cd21AdFd70c47d70BDb063",
      "chainId": 552,
      "name": "Craft",
      "symbol": "CFT",
      "decimals": 18,
      "logoURI": "https://i.imgur.com/NKhDk4v.png"
    }
  ]
}
